LICENSE
README.md
fastrand_fields/__init__.py
fastrand_fields/adjectives.py
fastrand_fields/nouns.py
fastrand_fields-0.1.2.dist-info/LICENSE
fastrand_fields-0.1.2.dist-info/WHEEL
fastrand_fields-0.1.2.dist-info/METADATA
fastrand_fields-0.1.2.dist-info/RECORD
